msimmusic/__init__.py
msimmusic/msimmusic.py
msimmusic-0.0.2.dist-info/LICENSE
msimmusic-0.0.2.dist-info/METADATA
msimmusic-0.0.2.dist-info/WHEEL
msimmusic-0.0.2.dist-info/top_level.txt
msimmusic-0.0.2.dist-info/RECORD
