Metadata-Version: 2.1
Name: msimmusic
Version: 0.0.2
Summary: Make Your MIDI Instrument. From the Tufts MSIM RPi Music Project
Home-page: https://github.com/homorhythm/msim2020
Author: Haiting Chan
Author-email: haitingchan@gmail.com
License: UNKNOWN
Platform: UNKNOWN
Classifier: Programming Language :: Python :: 3
Classifier: License :: OSI Approved :: MIT License
Classifier: Operating System :: OS Independent
Requires-Python: >=3.0
